geoagro/ADF_KPSS.py
geoagro/__init__.py
geoagro/all_cluster_segmentation.py
geoagro/centroid.py
geoagro/clip.py
geoagro/cluster.py
geoagro/cluster_TimeSeries.py
geoagro/cluster_new.py
geoagro/cluster_norm.py
geoagro/cluster_raw.py
geoagro/cluster_segmentation.py
geoagro/extract.py
geoagro/generate_clips.py
geoagro/generate_csv_file.py
geoagro/generate_fourth_cluster.py
geoagro/generate_gif.py
geoagro/generate_stack.py
geoagro/isolation_forest.py
geoagro/outliers_IQR.py
geoagro/plot_all_series_csv.py
geoagro/plot_interactive.py
geoagro/plot_props_series.py
geoagro/plot_series_csv.py
geoagro/properties_glob.py
geoagro/read_fourth_clusters.py
geoagro/run_pipeline.py
geoagro/sav_gol.py
geoagro/seasonal_csv.py
geoagro/tif_clustered.py
geoagro/visualize.py
geoagro/weather.py
geoagro_library-0.0.3.dist-info/METADATA
geoagro_library-0.0.3.dist-info/WHEEL
geoagro_library-0.0.3.dist-info/top_level.txt
geoagro_library-0.0.3.dist-info/RECORD
